<?xml version="1.0" encoding="utf-8"?><root name="CONTACT">    <!-- value format: HEX String -->    <entry name="Terminal Configuration">        <!-- AID -->        <item key="9F06" value="00000000000000000000000000000000" />        <!-- ICS -->        <item key="DF24" value="F4C0F0E8EF0E60" />        <!-- Transaction Currency Code -->        <item key="5F2A" value="0840" />        <!-- Transaction Reference Currency Conversion  -->        <item key="DF22" value="00000000" />        <!-- EC Terminal Support Indicator -->        <item key="9F7A" value="00" />        <!-- Terminal Type -->        <item key="9F35" value="22" />        <!-- Application Selection Indicator -->        <item key="DF01" value="01" />        <!-- Terminal Capabilities -->        <item key="9F33" value="E0F8C8" />        <!-- Additional Terminal Capabilities  -->        <item key="9F40" value="F000F0A001" />        <!-- Acquirer Identifier  -->        <item key="9F01" value="123456789000" />        <!-- Merchant Category Code  -->        <item key="9F15" value="1234" />        <!-- Merchant Identifier  -->        <item key="9F16" value="313233343536373839303132333435" />        <!-- Transaction Reference Currency Code  -->        <item key="9F3C" value="0840" />        <!-- Transaction Currency Exponent -->        <item key="5F36" value="02" />        <!-- Peference currency exponent -->        <item key="9F3D" value="02" />        <!-- Terminal Country Code -->        <item key="9F1A" value="0840" />        <!-- Interface Device (IFD) Serial Number -->        <item key="9F1E" value="3030303030313539" />        <!-- Terminal Identification -->        <item key="9F1C" value="3132333435363738" />        <!-- Reader Contactless Transaction Limit -->        <item key="9F7B" value="000000000000" />        <!-- Maximum Target Percentage to be used for Biased Random Selection -->        <item key="DF16" value="00" />        <!-- Target Percentage to be Used for Random Selection -->        <item key="DF17" value="00" />        <!-- Threshold Value for Biased Random Selection -->        <item key="DF15" value="000001F4" />        <!-- Terminal Floor Limit -->        <item key="9F1B" value="00000000" />        <!-- Default Dynamic Data Authentication Data Object List (DDOL) -->        <item key="DF44" value="9F3704" />        <!-- Default Transaction Certificate Data Object List (TDOL) -->        <item key="DF45" value="9F02065F2A029A039C0195059F3704" />        <!-- application version -->        <item key="9F09" value="0002" />        <item key="5F2D" value="656E" />    </entry>    <entry name="AID CT Unionpay">        <!-- AID -->        <item key="9F06" value="A0000003330101" />        <!-- TAC-Denial -->        <item key="DF13" value="0010000000" />        <!-- TAC-Online -->        <item key="DF12" value="FCF8E4F880" />        <!-- TAC-Default -->        <item key="DF11" value="FCF0E40800" />        <!-- Application Version Number -->        <item key="9F09" value="0030" />    </entry>    <entry name="AID CT VISA1">        <!-- AID -->        <item key="9F06" value="A0000000031010" />        <!-- TAC-Denial -->        <item key="DF13" value="0010000000" />        <!-- TAC-Online -->        <item key="DF12" value="DC4004F800" />        <!-- TAC-Default -->        <item key="DF11" value="DC4000A800" />        <!-- Application Version Number -->        <item key="9F09" value="008D" />        <!-- Terminal Capabilities -->        <item key="9F33" value="E0F8C8" />        <!-- Terminal Floor Limit -->        <item key="9F1B" value="00000000" />    </entry>    <entry name="AID CT VISA2">        <!-- AID -->        <item key="9F06" value="A0000000032010" />        <!-- TAC-Denial -->        <item key="DF13" value="0010000000" />        <!-- TAC-Online -->        <item key="DF12" value="DC4004F800" />        <!-- TAC-Default -->        <item key="DF11" value="DC4000A800" />        <!-- Application Version Number -->        <item key="9F09" value="0200" />        <!-- Terminal Capabilities -->        <item key="9F33" value="E0F8C8" />        <!-- Terminal Floor Limit -->        <item key="9F1B" value="00000000" />    </entry>    <entry name="AID CT VISA3">        <!-- AID -->        <item key="9F06" value="A0000000033010" />        <!-- TAC-Denial -->        <item key="DF13" value="0010000000" />        <!-- TAC-Online -->        <item key="DF12" value="DC4004F800" />        <!-- TAC-Default -->        <item key="DF11" value="DC4000A800" />        <!-- Application Version Number -->        <item key="9F09" value="008D" />        <!-- Terminal Capabilities -->        <item key="9F33" value="E0F8C8" />        <!-- Terminal Floor Limit -->        <item key="9F1B" value="00000000" />    </entry>    <entry name="AID CT VISA4">        <!-- AID -->        <item key="9F06" value="A0000000980840" />        <!-- TAC-Denial -->        <item key="DF13" value="0010000000" />        <!-- TAC-Online -->        <item key="DF12" value="DC4004F800" />        <!-- TAC-Default -->        <item key="DF11" value="DC4000A800" />        <!-- Application Version Number -->        <item key="9F09" value="008D" />        <!-- Terminal Capabilities -->        <item key="9F33" value="E0F8C8" />        <!-- Terminal Floor Limit -->        <item key="9F1B" value="00000000" />    </entry>    <entry name="AID CT MASTER1">        <!-- AID -->        <item key="9F06" value="A0000000041010" />        <!-- Terminal Capabilities -->        <item key="9F33" value="E0F8C8" />        <!-- TAC-Denial -->        <item key="DF13" value="0000000000" />        <!-- TAC-Online -->        <item key="DF12" value="FC50BCF800" />        <!-- TAC-Default -->        <item key="DF11" value="FC50BCA000" />        <!-- Application Version Number -->        <item key="9F09" value="0002" />        <!-- Terminal Floor Limit -->        <item key="9F1B" value="00000000" />        <!-- Terminal Risk Management Data -->        <item key="9F1D" value="6C78800000000000" />    </entry>    <entry name="AID CT MASTER5">        <!-- AID -->        <item key="9F06" value="A0000000042203" />        <!-- TAC-Denial -->        <item key="DF13" value="0000000000" />        <!-- TAC-Online -->        <item key="DF12" value="FC50BCF800" />        <!-- TAC-Default -->        <item key="DF11" value="FC50BCA000" />        <!-- Application Version Number -->        <item key="9F09" value="0002" />        <!-- Terminal Floor Limit -->        <item key="9F1B" value="00000000" />    </entry>    <entry name="AID CT MASTER2">        <!-- AID -->        <item key="9F06" value="A0000000043060" />        <!-- TAC-Denial -->        <item key="DF13" value="0000000000" />        <!-- TAC-Online -->        <item key="DF12" value="FC50BCF800" />        <!-- TAC-Default -->        <item key="DF11" value="FC50BCA000" />        <!-- Application Version Number -->        <item key="9F09" value="0002" />        <!-- Terminal Floor Limit -->        <item key="9F1B" value="00000000" />        <!-- Terminal Risk Management Data -->        <item key="9F1D" value="4C78800000000000" />    </entry>    <entry name="AID CT MASTER4">        <!-- AID -->        <item key="9F06" value="A0000000046010" />        <!-- TAC-Denial -->        <item key="DF13" value="0400000000" />        <!-- TAC-Online -->        <item key="DF12" value="F850ACF800" />        <!-- TAC-Default -->        <item key="DF11" value="FC50ACA000" />        <!-- Application Version Number -->        <item key="9F09" value="0002" />        <!-- Terminal Risk Management Data -->        <item key="9F1D" value="4C78800000000000" />    </entry>    <entry name="AID CT TEST5">        <!-- AID -->        <item key="9F06" value="A0000000101030" />        <!-- TAC-Denial -->        <item key="DF13" value="0400000000" />        <!-- TAC-Online -->        <item key="DF12" value="F850ACF800" />        <!-- TAC-Default -->        <item key="DF11" value="FC50ACA000" />        <!-- Application Version Number -->        <item key="9F09" value="0002" />        <!-- Terminal Risk Management Data -->        <item key="9F1D" value="4C78800000000000" />    </entry>    <entry name="AID CT AMEX">        <!-- AID -->        <item key="9F06" value="A00000002501" />        <!-- TAC-Denial -->        <item key="DF13" value="0000000000" />        <!-- TAC-Online -->        <item key="DF12" value="0000000000" />        <!-- TAC-Default -->        <item key="DF11" value="0000000000" />        <!-- Application Version Number -->        <item key="9F09" value="0001" />        <item key="9F1B" value="00000000" />    </entry>    <entry name="AID CT DISCOVER1">        <!-- AID -->        <item key="9F06" value="A0000003241010" />        <!-- Newland Custom Tag - 1F811F -->        <CUSTOM name="CUSTOMTAG01">            <!-- Custom Tag Name -->            <item key="Tag name" value="9F6E" />            <!-- Tag Template1 -->            <item key="Template1" value="0" />            <!-- Tag Template2 -->            <item key="Template2" value="0" />            <!-- Tag Source -->            <item key="Source" value="02" />            <!-- Tag Format -->            <item key="Format" value="03" />            <!-- Tag Min Lenth -->            <item key="Min lenth" value="08" />            <!-- Tag Max Lenth -->            <item key="Max lenth" value="08" />        </CUSTOM>    </entry>    <entry name="AID CT DISCOVER2">        <!-- AID -->        <item key="9F06" value="A0000001523010" />        <!-- TAC-Denial -->        <item key="DF13" value="0000000000" />        <!-- TAC-Online -->        <item key="DF12" value="FCE09CF800" />        <!-- TAC-Default -->        <item key="DF11" value="DC0000A000" />        <!-- Application Version Number -->        <item key="9F09" value="0001" />        <!-- Terminal Floor Limit -->        <item key="9F1B" value="00000000" />        <!-- Newland Custom Tag - 1F811F -->        <CUSTOM name="CUSTOMTAG01">            <!-- Custom Tag Name -->            <item key="Tag name" value="9F6E" />            <!-- Tag Template1 -->            <item key="Template1" value="0" />            <!-- Tag Template2 -->            <item key="Template2" value="0" />            <!-- Tag Source -->            <item key="Source" value="02" />            <!-- Tag Format -->            <item key="Format" value="03" />            <!-- Tag Min Lenth -->            <item key="Min lenth" value="08" />            <!-- Tag Max Lenth -->            <item key="Max lenth" value="08" />        </CUSTOM>        <!-- Custom Tag End -->    </entry>    <entry name="AID CT DISCOVER3">        <!-- AID -->        <item key="9F06" value="A0000001524010" />        <!-- TAC-Denial -->        <item key="DF13" value="0010000000" />        <!-- TAC-Online -->        <item key="DF12" value="FCE09CF800" />        <!-- TAC-Default -->        <item key="DF11" value="DC0000A000" />        <!-- Application Version Number -->        <item key="9F09" value="0001" />        <!-- Terminal Floor Limit -->        <item key="9F1B" value="00000000" />        <!-- Newland Custom Tag - 1F811F -->        <CUSTOM name="CUSTOMTAG01">            <!-- Custom Tag Name -->            <item key="Tag name" value="9F6E" />            <!-- Tag Template1 -->            <item key="Template1" value="0" />            <!-- Tag Template2 -->            <item key="Template2" value="0" />            <!-- Tag Source -->            <item key="Source" value="02" />            <!-- Tag Format -->            <item key="Format" value="03" />            <!-- Tag Min Lenth -->            <item key="Min lenth" value="08" />            <!-- Tag Max Lenth -->            <item key="Max lenth" value="08" />        </CUSTOM>    </entry>    <entry name="AID CT JCB">        <!-- AID -->        <item key="9F06" value="A0000000651010" />        <!-- TAC-Denial -->        <item key="DF13" value="0010000000" />        <!-- TAC-Online -->        <item key="DF12" value="FC60ACF800" />        <!-- TAC-Default -->        <item key="DF11" value="FC6024A800" />        <!-- Application Version Number -->        <item key="9F09" value="0200" />        <!-- Maximum Target Percentage to be used for Biased Random Selection -->        <item key="DF16" value="00" />        <!-- Target Percentage to be Used for Random Selection -->        <item key="DF17" value="00" />        <!-- Threshold Value for Biased Random Selection -->        <item key="DF15" value="00000000" />        <item key="9F1B" value="00000000" />    </entry>    <entry name="AID CT MCCS">        <!-- AID -->        <item key="9F06" value="A0000006150001" />        <!-- TAC-Denial -->        <item key="DF13" value="0000880000" />        <!-- TAC-Online -->        <item key="DF12" value="B050149800" />        <!-- TAC-Default -->        <item key="DF11" value="B050148800" />        <!-- Application Version Number -->        <item key="9F09" value="0001" />        <!-- Additional Terminal Capabilities  -->        <item key="9F40" value="7000F0A200" />        <!-- ICS -->        <item key="DF24" value="F0C0C0F0EF0E62" />    </entry>    <entry name="AID CT RUPAY">        <!-- AID -->        <item key="9F06" value="A0000005241010" />    </entry>    <entry name="AID CT INTERAC">        <!-- AID -->        <item key="9F06" value="A0000002771010" />        <!--  Capability -->        <item key="9F33" value="E0F8C8" />        <!-- TAC-Denial -->        <item key="DF13" value="0010000000" />        <!-- TAC-Online -->        <item key="DF12" value="DC4004F800" />        <!-- TAC-Default -->        <item key="DF11" value="DC4000A800" />        <!-- Application Version Number -->        <item key="9F09" value="0001" />        <!-- Terminal Country Code -->        <item key="9F1A" value="0124" />        <!-- Transaction Currency Code -->        <item key="5F2A" value="0124" />    </entry>    <entry name="AID CT EMVTEST">        <!-- AID -->        <item key="9F06" value="A0000000999090" />        <!-- TAC-Denial -->        <item key="DF13" value="0010000000" />        <!-- TAC-Online -->        <item key="DF12" value="D84004F800" />        <!-- TAC-Default -->        <item key="DF11" value="D84000A800" />        <!-- Application Version Number -->        <item key="9F09" value="008C" />    </entry></root>